README.rst
setup.py
exodus/__init__.py
exodus/version.py
exodus.egg-info/PKG-INFO
exodus.egg-info/SOURCES.txt
exodus.egg-info/dependency_links.txt
exodus.egg-info/requires.txt
exodus.egg-info/top_level.txt