Metadata-Version: 1.1
Name: exodus
Version: 1.0.8
Summary: A light-weight, storage agnostic, data migration framework
Home-page: https://github.com/adamlwgriffiths/exodus
Author: Adam Griffiths
Author-email: UNKNOWN
License: BSD
Platform: any
Classifier: Natural Language :: English
Classifier: Intended Audience :: Developers
Classifier: Operating System :: MacOS :: MacOS X
Classifier: Operating System :: Microsoft :: Windows
Classifier: Operating System :: POSIX
Classifier: Programming Language :: Python
Classifier: License :: OSI Approved :: BSD License
Classifier: Topic :: Software Development :: Libraries
Classifier: Topic :: Software Development :: Libraries :: Python Modules
